glueather/__init__.py
glueather/__main__.py
glueather/ui_mainwindow.py
glueather/weathermanager.py
glueather-1.1.0.dist-info/LICENSE
glueather-1.1.0.dist-info/METADATA
glueather-1.1.0.dist-info/WHEEL
glueather-1.1.0.dist-info/entry_points.txt
glueather-1.1.0.dist-info/top_level.txt
glueather-1.1.0.dist-info/RECORD
