Metadata-Version: 2.1
Name: glueather
Version: 1.1.0
Summary: A simple Python/Qt weather application using the OpenWeather API
Home-page: https://github.com/vascocosta/glueather
Author: Vasco Costa
Author-email: vascomacosta@gmail.com
License: GPLv3
Project-URL: Bug Tracker, https://github.com/vascocosta/glueather/issues
Platform: UNKNOWN
Classifier: Programming Language :: Python :: 3
Classifier: License :: OSI Approved :: GNU General Public License v3 (GPLv3)
Classifier: Operating System :: OS Independent
Requires-Python: >=3.6
Requires-Dist: pyowm
Requires-Dist: pyqt5
